[
{"name": "AC", "value": "R$ 349,22"},
{"name": "AL", "value": "R$ 347,38"},
{"name": "AM", "value": "R$ 437,86"},
{"name": "AP", "value": "R$ 385,85"},
{"name": "BA", "value": "R$ 337,84"},
{"name": "CE", "value": "R$ 387,63"},
{"name": "DF", "value": "R$ 438,69"},
{"name": "ES", "value": "R$ 401,38"},
{"name": "GO", "value": "R$ 371,80"},
{"name": "MA", "value": "R$ 355,29"},
{"name": "MG", "value": "R$ 400,29"},
{"name": "MS", "value": "R$ 387,87"},
{"name": "MT", "value": "R$ 402,57"},
{"name": "PA", "value": "R$ 406,86"},
{"name": "PB", "value": "R$ 360,66"},
{"name": "PE", "value": "R$ 349,96"},
{"name": "PI", "value": "R$ 377,93"},
{"name": "PR", "value": "R$ 392,75"},
{"name": "RJ", "value": "R$ 430,56"},
{"name": "RN", "value": "R$ 331,79"},
{"name": "RO", "value": "R$ 359,68"},
{"name": "RR", "value": "R$ 403,83"},
{"name": "RS", "value": "R$ 416,82"},
{"name": "SC", "value": "R$ 430,69"},
{"name": "SE", "value": "R$ 362,09"},
{"name": "SP", "value": "R$ 443,40"},
{"name": "TO", "value": "R$ 364,49"}
]